sourmash-4.9.4.dist-info/METADATA
sourmash-4.9.4.dist-info/WHEEL
sourmash-4.9.4.dist-info/entry_points.txt
sourmash-4.9.4.dist-info/licenses/LICENSE
sourmash/__init__.py
sourmash/__main__.py
sourmash/_lowlevel/__init__.py
sourmash/_lowlevel/ffi.py
sourmash/_lowlevel/lib_lowlevel.so
sourmash/cli/.gitignore
sourmash/cli/__init__.py
sourmash/cli/categorize.py
sourmash/cli/compare.py
sourmash/cli/compute.py
sourmash/cli/gather.py
sourmash/cli/import_csv.py
sourmash/cli/index.py
sourmash/cli/info.py
sourmash/cli/lca/__init__.py
sourmash/cli/lca/classify.py
sourmash/cli/lca/compare_csv.py
sourmash/cli/lca/index.py
sourmash/cli/lca/rankinfo.py
sourmash/cli/lca/summarize.py
sourmash/cli/migrate.py
sourmash/cli/multigather.py
sourmash/cli/plot.py
sourmash/cli/prefetch.py
sourmash/cli/sbt_combine.py
sourmash/cli/scripts/__init__.py
sourmash/cli/search.py
sourmash/cli/sig/__init__.py
sourmash/cli/sig/cat.py
sourmash/cli/sig/check.py
sourmash/cli/sig/collect.py
sourmash/cli/sig/describe.py
sourmash/cli/sig/downsample.py
sourmash/cli/sig/export.py
sourmash/cli/sig/extract.py
sourmash/cli/sig/fileinfo.py
sourmash/cli/sig/filter.py
sourmash/cli/sig/flatten.py
sourmash/cli/sig/grep.py
sourmash/cli/sig/inflate.py
sourmash/cli/sig/ingest.py
sourmash/cli/sig/intersect.py
sourmash/cli/sig/kmers.py
sourmash/cli/sig/manifest.py
sourmash/cli/sig/merge.py
sourmash/cli/sig/overlap.py
sourmash/cli/sig/rename.py
sourmash/cli/sig/split.py
sourmash/cli/sig/subtract.py
sourmash/cli/sketch/__init__.py
sourmash/cli/sketch/dna.py
sourmash/cli/sketch/fromfile.py
sourmash/cli/sketch/protein.py
sourmash/cli/sketch/translate.py
sourmash/cli/storage/__init__.py
sourmash/cli/storage/convert.py
sourmash/cli/tax/__init__.py
sourmash/cli/tax/annotate.py
sourmash/cli/tax/genome.py
sourmash/cli/tax/grep.py
sourmash/cli/tax/metagenome.py
sourmash/cli/tax/prepare.py
sourmash/cli/tax/summarize.py
sourmash/cli/utils.py
sourmash/cli/watch.py
sourmash/command_compute.py
sourmash/command_sketch.py
sourmash/commands.py
sourmash/compare.py
sourmash/distance_utils.py
sourmash/exceptions.py
sourmash/fig.py
sourmash/hll.py
sourmash/index/__init__.py
sourmash-4.9.4.dist-info/RECORD
