Metadata-Version: 2.4
Name: sourmash
Version: 4.9.4
Classifier: Development Status :: 5 - Production/Stable
Classifier: Environment :: Console
Classifier: Environment :: MacOS X
Classifier: Intended Audience :: Science/Research
Classifier: Natural Language :: English
Classifier: Operating System :: POSIX :: Linux
Classifier: Operating System :: MacOS :: MacOS X
Classifier: Programming Language :: Rust
Classifier: Programming Language :: Python :: 3.13
Classifier: Programming Language :: Python :: 3.12
Classifier: Programming Language :: Python :: 3.11
Classifier: Topic :: Scientific/Engineering :: Bio-Informatics
Requires-Dist: screed>=1.1.3,<2
Requires-Dist: cffi>=1.14.0
Requires-Dist: numpy
Requires-Dist: matplotlib
Requires-Dist: scipy
Requires-Dist: deprecation>=2.0.6
Requires-Dist: cachetools>=4,<7
Requires-Dist: bitstring>=3.1.9,<5
Requires-Dist: pytest>=6.2.4,<8.5.0 ; extra == 'test'
Requires-Dist: pytest-cov>=4,<7.0 ; extra == 'test'
Requires-Dist: pytest-xdist>=3.1 ; extra == 'test'
Requires-Dist: pyyaml>=6,<7 ; extra == 'test'
Requires-Dist: diff-cover>=7.3 ; extra == 'test'
Requires-Dist: covdefaults>=2.2.2 ; extra == 'test'
Requires-Dist: recommonmark ; extra == 'test'
Requires-Dist: hypothesis ; extra == 'test'
Requires-Dist: build ; extra == 'test'
Requires-Dist: jupyter ; extra == 'demo'
Requires-Dist: jupyter-client ; extra == 'demo'
Requires-Dist: ipython ; extra == 'demo'
Requires-Dist: sphinx>=6,<9 ; extra == 'doc'
Requires-Dist: myst-parser ; extra == 'doc'
Requires-Dist: jinja2 ; extra == 'doc'
Requires-Dist: alabaster ; extra == 'doc'
Requires-Dist: sphinxcontrib-napoleon ; extra == 'doc'
Requires-Dist: nbsphinx ; extra == 'doc'
Requires-Dist: sphinx-design==0.6.1 ; extra == 'doc'
Requires-Dist: ipython ; extra == 'doc'
Requires-Dist: sphinx-copybutton ; extra == 'doc'
Requires-Dist: ipfshttpclient>=0.4.13 ; extra == 'storage'
Requires-Dist: redis ; extra == 'storage'
Requires-Dist: sourmash[test,demo,doc,storage] ; extra == 'all'
Provides-Extra: test
Provides-Extra: demo
Provides-Extra: doc
Provides-Extra: storage
Provides-Extra: all
License-File: LICENSE
Summary: tools for comparing biological sequences with k-mer sketches
Author: Luiz Irber, N. Tessa Pierce-Ward, Mohamed Abuelanin, Harriet Alexander, Abhishek Anant, Keya Barve, Colton Baumler, Olga Botvinnik, Phillip Brooks, Luca Cappelletti, Peter Cock, Daniel Dsouza, Jade Gardner, Laurent Gautier, Tim Head, Mahmudur Rahman Hera, Hannah Eve Houts, Lisa K. Johnson, Fabian Klötzl, David Koslicki, Katrin Leinweber, Marisa Lim, Ricky Lim, Chase Mateusiak, Bradley Nelson, Ivan Ogasawara, Aiden Pike, Taylor Reiter, Camille Scott, Andreas Sjödin, Connor T. Skennerton, 
Maintainer-email: "Luiz C. Irber, Jr" <luiz@sourmash.bio>, "C. Titus Brown" <titus@idyll.org>, "N. Tessa Pierce-Ward" <ntpierce@ucdavis.edu>
License-Expression: BSD-3-Clause
Requires-Python: >=3.11
Project-URL: Homepage, https://sourmash.bio/
Project-URL: Documentation, https://sourmash.readthedocs.io
Project-URL: CI, https://github.com/sourmash-bio/sourmash/actions
Project-URL: Source, https://github.com/sourmash-bio/sourmash
Project-URL: Tracker, https://github.com/sourmash-bio/sourmash/issues
